Filechan/___init__.py
Filechan/filechan.py
Filechan-0.0.6.dist-info/LICENSE
Filechan-0.0.6.dist-info/METADATA
Filechan-0.0.6.dist-info/WHEEL
Filechan-0.0.6.dist-info/top_level.txt
Filechan-0.0.6.dist-info/RECORD
