Metadata-Version: 2.1
Name: Filechan
Version: 0.0.6
Summary: Simple FileChan Module
Author: Mugunthan
Author-email: the.mugunthan@gmail.com
Keywords: filechan,filechan-api
Classifier: Programming Language :: Python :: 3.8
Classifier: License :: OSI Approved :: MIT License
Classifier: Natural Language :: English
Classifier: Operating System :: OS Independent
Requires-Python: >=3
License-File: LICENSE
Requires-Dist: beautifulSoup4
Requires-Dist: requests
Requires-Dist: requests-toolbelt
